<?xml version="1.0" encoding="UTF-8" ?>
<!DOCTYPE mapper PUBLIC "-//mybatis.org//DTD Mapper 3.0//EN" "http://mybatis.org/dtd/mybatis-3-mapper.dtd" >
<mapper namespace="com.core.dao.TWxSubsMapper" >
  <resultMap id="BaseResultMap" type="com.core.model.TWxSubs" >
    <!--
      WARNING - @mbggenerated
      This element is automatically generated by MyBatis Generator, do not modify.
    -->
    <constructor >
      <idArg column="ID" jdbcType="VARCHAR" javaType="java.lang.String" />
      <arg column="APPID" jdbcType="VARCHAR" javaType="java.lang.String" />
      <arg column="OPENID" jdbcType="VARCHAR" javaType="java.lang.String" />
      <arg column="SUBSCRIBETIME" jdbcType="TIMESTAMP" javaType="java.util.Date" />
      <arg column="NICKNAME" jdbcType="VARCHAR" javaType="java.lang.String" />
      <arg column="USER_LOGIN_NAME" jdbcType="VARCHAR" javaType="java.lang.String" />
      <arg column="DEPT_CODE" jdbcType="VARCHAR" javaType="java.lang.String" />
      <arg column="SEX" jdbcType="VARCHAR" javaType="java.lang.String" />
      <arg column="CITY_CODE" jdbcType="VARCHAR" javaType="java.lang.String" />
      <arg column="COUNTRY_CODE" jdbcType="VARCHAR" javaType="java.lang.String" />
      <arg column="PROVINCE_CODE" jdbcType="VARCHAR" javaType="java.lang.String" />
      <arg column="LANGUAGE" jdbcType="VARCHAR" javaType="java.lang.String" />
      <arg column="HEADIMGURL" jdbcType="VARCHAR" javaType="java.lang.String" />
      <arg column="UNIONID" jdbcType="VARCHAR" javaType="java.lang.String" />
      <arg column="CREATE_TIME" jdbcType="TIMESTAMP" javaType="java.util.Date" />
      <arg column="UPDATE_TIME" jdbcType="TIMESTAMP" javaType="java.util.Date" />
      <arg column=" PARENT_ID" jdbcType="VARCHAR" javaType="java.lang.String" />
    </constructor>
  </resultMap>
  <sql id="Example_Where_Clause" >
    <!--
      WARNING - @mbggenerated
      This element is automatically generated by MyBatis Generator, do not modify.
    -->
    <where >
      <foreach collection="oredCriteria" item="criteria" separator="or" >
        <if test="criteria.valid" >
          <trim prefix="(" suffix=")" prefixOverrides="and" >
            <foreach collection="criteria.criteria" item="criterion" >
              <choose >
                <when test="criterion.noValue" >
                  and ${criterion.condition}
                </when>
                <when test="criterion.singleValue" >
                  and ${criterion.condition} #{criterion.value}
                </when>
                <when test="criterion.betweenValue" >
                  and ${criterion.condition} #{criterion.value} and #{criterion.secondValue}
                </when>
                <when test="criterion.listValue" >
                  and ${criterion.condition}
                  <foreach collection="criterion.value" item="listItem" open="(" close=")" separator="," >
                    #{listItem}
                  </foreach>
                </when>
              </choose>
            </foreach>
          </trim>
        </if>
      </foreach>
    </where>
  </sql>
  <sql id="Update_By_Example_Where_Clause" >
    <!--
      WARNING - @mbggenerated
      This element is automatically generated by MyBatis Generator, do not modify.
    -->
    <where >
      <foreach collection="example.oredCriteria" item="criteria" separator="or" >
        <if test="criteria.valid" >
          <trim prefix="(" suffix=")" prefixOverrides="and" >
            <foreach collection="criteria.criteria" item="criterion" >
              <choose >
                <when test="criterion.noValue" >
                  and ${criterion.condition}
                </when>
                <when test="criterion.singleValue" >
                  and ${criterion.condition} #{criterion.value}
                </when>
                <when test="criterion.betweenValue" >
                  and ${criterion.condition} #{criterion.value} and #{criterion.secondValue}
                </when>
                <when test="criterion.listValue" >
                  and ${criterion.condition}
                  <foreach collection="criterion.value" item="listItem" open="(" close=")" separator="," >
                    #{listItem}
                  </foreach>
                </when>
              </choose>
            </foreach>
          </trim>
        </if>
      </foreach>
    </where>
  </sql>
  <sql id="Base_Column_List" >
    <!--
      WARNING - @mbggenerated
      This element is automatically generated by MyBatis Generator, do not modify.
    -->
    ID, APPID, OPENID, SUBSCRIBETIME, NICKNAME, USER_LOGIN_NAME, DEPT_CODE, SEX, CITY_CODE, 
    COUNTRY_CODE, PROVINCE_CODE, LANGUAGE, HEADIMGURL, UNIONID, CREATE_TIME, UPDATE_TIME, 
    " PARENT_ID"
  </sql>
  <select id="selectByExample" resultMap="BaseResultMap" parameterType="com.core.model.TWxSubsExample" >
    <!--
      WARNING - @mbggenerated
      This element is automatically generated by MyBatis Generator, do not modify.
    -->
    select
    <if test="distinct" >
      distinct
    </if>
    <include refid="Base_Column_List" />
    from t_wx_subs
    <if test="_parameter != null" >
      <include refid="Example_Where_Clause" />
    </if>
    <if test="orderByClause != null" >
      order by ${orderByClause}
    </if>
  </select>
  <delete id="deleteByExample" parameterType="com.core.model.TWxSubsExample" >
    <!--
      WARNING - @mbggenerated
      This element is automatically generated by MyBatis Generator, do not modify.
    -->
    delete from t_wx_subs
    <if test="_parameter != null" >
      <include refid="Example_Where_Clause" />
    </if>
  </delete>
  <insert id="insertSelective" parameterType="com.core.model.TWxSubs" >
    <!--
      WARNING - @mbggenerated
      This element is automatically generated by MyBatis Generator, do not modify.
    -->
    insert into t_wx_subs
    <trim prefix="(" suffix=")" suffixOverrides="," >
      <if test="id != null" >
        ID,
      </if>
      <if test="appid != null" >
        APPID,
      </if>
      <if test="openid != null" >
        OPENID,
      </if>
      <if test="subscribetime != null" >
        SUBSCRIBETIME,
      </if>
      <if test="nickname != null" >
        NICKNAME,
      </if>
      <if test="userLoginName != null" >
        USER_LOGIN_NAME,
      </if>
      <if test="deptCode != null" >
        DEPT_CODE,
      </if>
      <if test="sex != null" >
        SEX,
      </if>
      <if test="cityCode != null" >
        CITY_CODE,
      </if>
      <if test="countryCode != null" >
        COUNTRY_CODE,
      </if>
      <if test="provinceCode != null" >
        PROVINCE_CODE,
      </if>
      <if test="language != null" >
        LANGUAGE,
      </if>
      <if test="headimgurl != null" >
        HEADIMGURL,
      </if>
      <if test="unionid != null" >
        UNIONID,
      </if>
      <if test="createTime != null" >
        CREATE_TIME,
      </if>
      <if test="updateTime != null" >
        UPDATE_TIME,
      </if>
      <if test="parentId != null" >
        " PARENT_ID",
      </if>
    </trim>
    <trim prefix="values (" suffix=")" suffixOverrides="," >
      <if test="id != null" >
        #{id,jdbcType=VARCHAR},
      </if>
      <if test="appid != null" >
        #{appid,jdbcType=VARCHAR},
      </if>
      <if test="openid != null" >
        #{openid,jdbcType=VARCHAR},
      </if>
      <if test="subscribetime != null" >
        #{subscribetime,jdbcType=TIMESTAMP},
      </if>
      <if test="nickname != null" >
        #{nickname,jdbcType=VARCHAR},
      </if>
      <if test="userLoginName != null" >
        #{userLoginName,jdbcType=VARCHAR},
      </if>
      <if test="deptCode != null" >
        #{deptCode,jdbcType=VARCHAR},
      </if>
      <if test="sex != null" >
        #{sex,jdbcType=VARCHAR},
      </if>
      <if test="cityCode != null" >
        #{cityCode,jdbcType=VARCHAR},
      </if>
      <if test="countryCode != null" >
        #{countryCode,jdbcType=VARCHAR},
      </if>
      <if test="provinceCode != null" >
        #{provinceCode,jdbcType=VARCHAR},
      </if>
      <if test="language != null" >
        #{language,jdbcType=VARCHAR},
      </if>
      <if test="headimgurl != null" >
        #{headimgurl,jdbcType=VARCHAR},
      </if>
      <if test="unionid != null" >
        #{unionid,jdbcType=VARCHAR},
      </if>
      <if test="createTime != null" >
        #{createTime,jdbcType=TIMESTAMP},
      </if>
      <if test="updateTime != null" >
        #{updateTime,jdbcType=TIMESTAMP},
      </if>
      <if test="parentId != null" >
        #{parentId,jdbcType=VARCHAR},
      </if>
    </trim>
  </insert>
  <select id="countByExample" parameterType="com.core.model.TWxSubsExample" resultType="java.lang.Integer" >
    <!--
      WARNING - @mbggenerated
      This element is automatically generated by MyBatis Generator, do not modify.
    -->
    select count(*) from t_wx_subs
    <if test="_parameter != null" >
      <include refid="Example_Where_Clause" />
    </if>
  </select>
  <update id="updateByExampleSelective" parameterType="map" >
    <!--
      WARNING - @mbggenerated
      This element is automatically generated by MyBatis Generator, do not modify.
    -->
    update t_wx_subs
    <set >
      <if test="record.id != null" >
        ID = #{record.id,jdbcType=VARCHAR},
      </if>
      <if test="record.appid != null" >
        APPID = #{record.appid,jdbcType=VARCHAR},
      </if>
      <if test="record.openid != null" >
        OPENID = #{record.openid,jdbcType=VARCHAR},
      </if>
      <if test="record.subscribetime != null" >
        SUBSCRIBETIME = #{record.subscribetime,jdbcType=TIMESTAMP},
      </if>
      <if test="record.nickname != null" >
        NICKNAME = #{record.nickname,jdbcType=VARCHAR},
      </if>
      <if test="record.userLoginName != null" >
        USER_LOGIN_NAME = #{record.userLoginName,jdbcType=VARCHAR},
      </if>
      <if test="record.deptCode != null" >
        DEPT_CODE = #{record.deptCode,jdbcType=VARCHAR},
      </if>
      <if test="record.sex != null" >
        SEX = #{record.sex,jdbcType=VARCHAR},
      </if>
      <if test="record.cityCode != null" >
        CITY_CODE = #{record.cityCode,jdbcType=VARCHAR},
      </if>
      <if test="record.countryCode != null" >
        COUNTRY_CODE = #{record.countryCode,jdbcType=VARCHAR},
      </if>
      <if test="record.provinceCode != null" >
        PROVINCE_CODE = #{record.provinceCode,jdbcType=VARCHAR},
      </if>
      <if test="record.language != null" >
        LANGUAGE = #{record.language,jdbcType=VARCHAR},
      </if>
      <if test="record.headimgurl != null" >
        HEADIMGURL = #{record.headimgurl,jdbcType=VARCHAR},
      </if>
      <if test="record.unionid != null" >
        UNIONID = #{record.unionid,jdbcType=VARCHAR},
      </if>
      <if test="record.createTime != null" >
        CREATE_TIME = #{record.createTime,jdbcType=TIMESTAMP},
      </if>
      <if test="record.updateTime != null" >
        UPDATE_TIME = #{record.updateTime,jdbcType=TIMESTAMP},
      </if>
      <if test="record.parentId != null" >
        " PARENT_ID" = #{record.parentId,jdbcType=VARCHAR},
      </if>
    </set>
    <if test="_parameter != null" >
      <include refid="Update_By_Example_Where_Clause" />
    </if>
  </update>
  <update id="updateByExample" parameterType="map" >
    <!--
      WARNING - @mbggenerated
      This element is automatically generated by MyBatis Generator, do not modify.
    -->
    update t_wx_subs
    set ID = #{record.id,jdbcType=VARCHAR},
      APPID = #{record.appid,jdbcType=VARCHAR},
      OPENID = #{record.openid,jdbcType=VARCHAR},
      SUBSCRIBETIME = #{record.subscribetime,jdbcType=TIMESTAMP},
      NICKNAME = #{record.nickname,jdbcType=VARCHAR},
      USER_LOGIN_NAME = #{record.userLoginName,jdbcType=VARCHAR},
      DEPT_CODE = #{record.deptCode,jdbcType=VARCHAR},
      SEX = #{record.sex,jdbcType=VARCHAR},
      CITY_CODE = #{record.cityCode,jdbcType=VARCHAR},
      COUNTRY_CODE = #{record.countryCode,jdbcType=VARCHAR},
      PROVINCE_CODE = #{record.provinceCode,jdbcType=VARCHAR},
      LANGUAGE = #{record.language,jdbcType=VARCHAR},
      HEADIMGURL = #{record.headimgurl,jdbcType=VARCHAR},
      UNIONID = #{record.unionid,jdbcType=VARCHAR},
      CREATE_TIME = #{record.createTime,jdbcType=TIMESTAMP},
      UPDATE_TIME = #{record.updateTime,jdbcType=TIMESTAMP},
      " PARENT_ID" = #{record.parentId,jdbcType=VARCHAR}
    <if test="_parameter != null" >
      <include refid="Update_By_Example_Where_Clause" />
    </if>
  </update>
  <update id="updateByPrimaryKeySelective" parameterType="com.core.model.TWxSubs" >
    <!--
      WARNING - @mbggenerated
      This element is automatically generated by MyBatis Generator, do not modify.
    -->
    update t_wx_subs
    <set >
      <if test="appid != null" >
        APPID = #{appid,jdbcType=VARCHAR},
      </if>
      <if test="openid != null" >
        OPENID = #{openid,jdbcType=VARCHAR},
      </if>
      <if test="subscribetime != null" >
        SUBSCRIBETIME = #{subscribetime,jdbcType=TIMESTAMP},
      </if>
      <if test="nickname != null" >
        NICKNAME = #{nickname,jdbcType=VARCHAR},
      </if>
      <if test="userLoginName != null" >
        USER_LOGIN_NAME = #{userLoginName,jdbcType=VARCHAR},
      </if>
      <if test="deptCode != null" >
        DEPT_CODE = #{deptCode,jdbcType=VARCHAR},
      </if>
      <if test="sex != null" >
        SEX = #{sex,jdbcType=VARCHAR},
      </if>
      <if test="cityCode != null" >
        CITY_CODE = #{cityCode,jdbcType=VARCHAR},
      </if>
      <if test="countryCode != null" >
        COUNTRY_CODE = #{countryCode,jdbcType=VARCHAR},
      </if>
      <if test="provinceCode != null" >
        PROVINCE_CODE = #{provinceCode,jdbcType=VARCHAR},
      </if>
      <if test="language != null" >
        LANGUAGE = #{language,jdbcType=VARCHAR},
      </if>
      <if test="headimgurl != null" >
        HEADIMGURL = #{headimgurl,jdbcType=VARCHAR},
      </if>
      <if test="unionid != null" >
        UNIONID = #{unionid,jdbcType=VARCHAR},
      </if>
      <if test="createTime != null" >
        CREATE_TIME = #{createTime,jdbcType=TIMESTAMP},
      </if>
      <if test="updateTime != null" >
        UPDATE_TIME = #{updateTime,jdbcType=TIMESTAMP},
      </if>
      <if test="parentId != null" >
        " PARENT_ID" = #{parentId,jdbcType=VARCHAR},
      </if>
    </set>
    where ID = #{id,jdbcType=VARCHAR}
  </update>
</mapper>